odoo/addons/sale_payment_term_security/README.rst
odoo/addons/sale_payment_term_security/__init__.py
odoo/addons/sale_payment_term_security/__manifest__.py
odoo/addons/sale_payment_term_security/i18n/es.po
odoo/addons/sale_payment_term_security/i18n/it.po
odoo/addons/sale_payment_term_security/i18n/sale_payment_term_security.pot
odoo/addons/sale_payment_term_security/models/__init__.py
odoo/addons/sale_payment_term_security/models/sale_order.py
odoo/addons/sale_payment_term_security/readme/CONFIGURE.md
odoo/addons/sale_payment_term_security/readme/CONTRIBUTORS.md
odoo/addons/sale_payment_term_security/readme/DESCRIPTION.md
odoo/addons/sale_payment_term_security/static/description/icon.png
odoo/addons/sale_payment_term_security/static/description/index.html
odoo/addons/sale_payment_term_security/tests/__init__.py
odoo/addons/sale_payment_term_security/tests/test_sale_payment_term_security.py
odoo_addon_sale_payment_term_security-17.0.1.0.0.4.dist-info/METADATA
odoo_addon_sale_payment_term_security-17.0.1.0.0.4.dist-info/WHEEL
odoo_addon_sale_payment_term_security-17.0.1.0.0.4.dist-info/top_level.txt
odoo_addon_sale_payment_term_security-17.0.1.0.0.4.dist-info/RECORD
